{"stats":{"minecraft:killed_by":{"minecraft:skeleton":1},"minecraft:crafted":{"minecraft:oak_planks":8,"minecraft:crafting_table":1,"minecraft:stick":12,"minecraft:wooden_pickaxe":1,"minecraft:cobblestone_stairs":4,"minecraft:bread":3},"minecraft:used":{"minecraft:wheat_seeds":16,"minecraft:cobblestone_stairs":3,"minecraft:birch_planks":3,"minecraft:wooden_pickaxe":13,"minecraft:torch":1,"minecraft:dirt":20,"minecraft:crafting_table":2,"minecraft:potato":10},"minecraft:dropped":{"minecraft:bread":3},"minecraft:picked_up":{"minecraft:stick":8,"minecraft:crafting_table":2,"minecraft:wheat":11,"minecraft:torch":1,"minecraft:birch_planks":10,"minecraft:oak_log":2,"minecraft:cobblestone_stairs":1,"minecraft:dirt":20,"minecraft:wheat_seeds":29,"minecraft:bread":1,"minecraft:cobblestone":12},"minecraft:mined":{"minecraft:birch_planks":10,"minecraft:wheat":15,"minecraft:cobblestone_stairs":1,"minecraft:crafting_table":1,"minecraft:grass":1,"minecraft:grass_block":16,"minecraft:dirt":2,"minecraft:stone":12,"minecraft:wall_torch":1},"minecraft:custom":{"minecraft:time_since_rest":2240,"minecraft:sprint_one_cm":59512,"minecraft:damage_taken":1566,"minecraft:walk_one_cm":58771,"minecraft:drop":1,"minecraft:damage_dealt":20,"minecraft:interact_with_crafting_table":8,"minecraft:swim_one_cm":597,"minecraft:fly_one_cm":51446,"minecraft:open_chest":3,"minecraft:play_one_minute":30829,"minecraft:crouch_one_cm":1938,"minecraft:deaths":5,"minecraft:sneak_time":2435,"minecraft:walk_under_water_one_cm":4141,"minecraft:jump":405,"minecraft:leave_game":1,"minecraft:walk_on_water_one_cm":18908,"minecraft:time_since_death":2213,"minecraft:climb_one_cm":4800,"minecraft:damage_resisted":204,"minecraft:fall_one_cm":11612}},"DataVersion":2580}